Workbook

Sheet Guidance
B8: Implementation Guidance This Excel sheet must be removed from the final version of the document.
B10: Design This spreadsheet has been designed using CertiKit's colour scheme. To choose a different table colour scheme, click in the table, select the Table Design menu tab and choose a different style. The same applies to the drop-down menu "slicers" at the top of the screen. Click in one slicer, then hold down the Shift key and click on the rest, one by one. This will select them all. Then click on the Slicer menu tab and choose a different style. You can also create your own table and slicer styles using your own colour scheme to reflect your organization's branding.
B12: Purpose of this document This document should be used to plan the project to implement an ISO22301-conformant business continuity management system.
B14: Areas of the standard addressed All areas of the ISO22301 standard are covered.
B16: General guidance This is an Excel version of a project plan that is also supplied in Microsoft Project format within the toolkit. It is intended for those users that do not have access to Microsoft Project. If you do have Project then we suggest you use that instead of this spreadsheet as it provides better project management functionality. The plan includes the main tasks involved in such a project, from initiation through to successful certification. You will need to decide on the likely duration of each of the tasks and update the resources that we have allocated to suit your own organization. It is difficult to reflect task dependencies within a spreadsheet but putting the tasks in approximate order of implementation will help to track progress. The Project Gantt chart is a pivot-table that displays the information from the Project plan in a more graphical form. Please note that you will need to click on the Refresh All button on the Data ribbon after each update.
B18: Toolkit version number ISO22301 Toolkit Version 6
B20: Copyright notice Except for any specifically identified third-party works included, this document has been authored by CertiKit, and is ©CertiKit except as stated below. CertiKit is a company registered in England and Wales with company number 6432088.
B22: Licence terms This document is licensed on and subject to the standard licence terms of CertiKit, available on request, or by download from our website. All other rights are reserved. Unless you have purchased this product you only have an evaluation licence. If this product was purchased, a full licence is granted to the person identified as the licensee in the relevant purchase order. The standard licence terms include special terms relating to any third party copyright included in this document.
B24: Disclaimer Please Note: Your use of and reliance on this document template is at your sole risk. Document templates are intended to be used as a starting point only from which you will create your own document and to which you will apply all reasonable quality checks before use. Therefore please note that it is your responsibility to ensure that the content of any document you create that is based on our templates is correct and appropriate for your needs and complies with relevant laws in your country. You should take all reasonable and proper legal and other professional advice before using this document. CertiKit makes no claims, promises, or guarantees about the accuracy, completeness, or adequacy of our document templates, assumes no duty of care to any person with respect its document templates or their contents, and expressly excludes and disclaims liability for any cost, expense, loss or damage suffered or incurred in reliance on our document templates, or in expectation of our document templates meeting your needs, including (without limitation) as a result of misstatements, errors and omissions in their contents.

Sheet Project Plan
B8: NOTE: All tasks and resources are approximations and will depend on the specifics of your project.
B10: REF | C10: TASK | D10: MAIN ISO22301 REF | E10: RESOURCE | F10: START DATE | G10: WORK DAYS | H10: END DATE | I10: COMPLETED DAYS | J10: PROGRESS
B11: 1 | C11: Project initiation | D11: All | E11: Project Mgr | G11: 0 | H11: =IFERROR(WORKDAY.INTL(ProjectPlanData[[#This Row],[START DATE]]-1,ProjectPlanData[[#This Row],[WORK DAYS]],1),"") | I11: 0 | J11: =IFERROR(ProjectPlanData[[#This Row],[COMPLETED DAYS]]/ProjectPlanData[[#This Row],[WORK DAYS]],"")
B12: 2 | C12: Define proposed scope of BCMS | D12: 4.3 Determining the scope of the business continuity management system | E12: Top Mgt,BC Manager | G12: 0 | H12: =IFERROR(WORKDAY.INTL(ProjectPlanData[[#This Row],[START DATE]]-1,ProjectPlanData[[#This Row],[WORK DAYS]],1),"") | I12: 0 | J12: =IFERROR(ProjectPlanData[[#This Row],[COMPLETED DAYS]]/ProjectPlanData[[#This Row],[WORK DAYS]],"")
B13: 3 | C13: Perform gap assessment | D13: All | E13: BC Manager,Business Reps | G13: 0 | H13: =IFERROR(WORKDAY.INTL(ProjectPlanData[[#This Row],[START DATE]]-1,ProjectPlanData[[#This Row],[WORK DAYS]],1),"") | I13: 0 | J13: =IFERROR(ProjectPlanData[[#This Row],[COMPLETED DAYS]]/ProjectPlanData[[#This Row],[WORK DAYS]],"")
B14: 4 | C14: Obtain Top Management commitment | D14: 5.1 Leadership and commitment | E14: BC Manager,Project Mgr,Top Mgt | G14: 0 | H14: =IFERROR(WORKDAY.INTL(ProjectPlanData[[#This Row],[START DATE]]-1,ProjectPlanData[[#This Row],[WORK DAYS]],1),"") | I14: 0 | J14: =IFERROR(ProjectPlanData[[#This Row],[COMPLETED DAYS]]/ProjectPlanData[[#This Row],[WORK DAYS]],"")
B15: 5 | C15: Establish BCMS document control | D15: 7.5 Documented information | E15: BC Manager,Project Mgr | G15: 0 | H15: =IFERROR(WORKDAY.INTL(ProjectPlanData[[#This Row],[START DATE]]-1,ProjectPlanData[[#This Row],[WORK DAYS]],1),"") | I15: 0 | J15: =IFERROR(ProjectPlanData[[#This Row],[COMPLETED DAYS]]/ProjectPlanData[[#This Row],[WORK DAYS]],"")
B16: 6 | C16: Define business continuity policy | D16: 5.2 Policy | E16: BC Manager,Top Mgt | G16: 0 | H16: =IFERROR(WORKDAY.INTL(ProjectPlanData[[#This Row],[START DATE]]-1,ProjectPlanData[[#This Row],[WORK DAYS]],1),"") | I16: 0 | J16: =IFERROR(ProjectPlanData[[#This Row],[COMPLETED DAYS]]/ProjectPlanData[[#This Row],[WORK DAYS]],"")
B17: 7 | C17: Document context of the organization | D17: 4. Context of the organization | E17: BC Manager,Top Mgt | G17: 0 | H17: =IFERROR(WORKDAY.INTL(ProjectPlanData[[#This Row],[START DATE]]-1,ProjectPlanData[[#This Row],[WORK DAYS]],1),"") | I17: 0 | J17: =IFERROR(ProjectPlanData[[#This Row],[COMPLETED DAYS]]/ProjectPlanData[[#This Row],[WORK DAYS]],"")
B18: 8 | C18: Agree business continuity objectives | D18: 6.2 Business continuity objectives and planning to achieve them | E18: BC Manager,Top Mgt | G18: 0 | H18: =IFERROR(WORKDAY.INTL(ProjectPlanData[[#This Row],[START DATE]]-1,ProjectPlanData[[#This Row],[WORK DAYS]],1),"") | I18: 0 | J18: =IFERROR(ProjectPlanData[[#This Row],[COMPLETED DAYS]]/ProjectPlanData[[#This Row],[WORK DAYS]],"")
B19: 9 | C19: Define roles, responsibilities and authorities | D19: 5.3 Roles, responsibilities and authorities | E19: BC Manager,Top Mgt | G19: 0 | H19: =IFERROR(WORKDAY.INTL(ProjectPlanData[[#This Row],[START DATE]]-1,ProjectPlanData[[#This Row],[WORK DAYS]],1),"") | I19: 0 | J19: =IFERROR(ProjectPlanData[[#This Row],[COMPLETED DAYS]]/ProjectPlanData[[#This Row],[WORK DAYS]],"")
B20: 10 | C20: Competence and training needs assessment | D20: 7.2 Competence | E20: BC Manager,Business Reps | G20: 0 | H20: =IFERROR(WORKDAY.INTL(ProjectPlanData[[#This Row],[START DATE]]-1,ProjectPlanData[[#This Row],[WORK DAYS]],1),"") | I20: 0 | J20: =IFERROR(ProjectPlanData[[#This Row],[COMPLETED DAYS]]/ProjectPlanData[[#This Row],[WORK DAYS]],"")
B21: 11 | C21: Conduct business impact analysis | D21: 8.2 Business impact analysis and risk assessment | E21: BC Manager,Business Reps,CIO | G21: 0 | H21: =IFERROR(WORKDAY.INTL(ProjectPlanData[[#This Row],[START DATE]]-1,ProjectPlanData[[#This Row],[WORK DAYS]],1),"") | I21: 0 | J21: =IFERROR(ProjectPlanData[[#This Row],[COMPLETED DAYS]]/ProjectPlanData[[#This Row],[WORK DAYS]],"")
B22: 12 | C22: Perform risk assessment | D22: 8.2 Business impact analysis and risk assessment | E22: BC Manager,Top Mgt,CIO | G22: 0 | H22: =IFERROR(WORKDAY.INTL(ProjectPlanData[[#This Row],[START DATE]]-1,ProjectPlanData[[#This Row],[WORK DAYS]],1),"") | I22: 0 | J22: =IFERROR(ProjectPlanData[[#This Row],[COMPLETED DAYS]]/ProjectPlanData[[#This Row],[WORK DAYS]],"")
... B34: 24 | C34: Post Project Review | D34: All | E34: Project Mgr,BC Manager,Top Mgt | G34: 0 | H34: =IFERROR(WORKDAY.INTL(ProjectPlanData[[#This Row],[START DATE]]-1,ProjectPlanData[[#This Row],[WORK DAYS]],1),"") | I34: 0 | J34: =IFERROR(ProjectPlanData[[#This Row],[COMPLETED DAYS]]/ProjectPlanData[[#This Row],[WORK DAYS]],"")

Sheet Project Budget
B8: NOTE: Budget items will depend on the specifics of your project.
B10: ITEM | C10: BUDGET | D10: SPENT TO DATE | E10: BUDGET REMAINING
B11: Internal resources | C11: 0 | D11: 0 | E11: =+ProjectBudget[[#This Row],[BUDGET]]-ProjectBudget[[#This Row],[SPENT TO DATE]] -> 0
B12: Training | C12: 0 | D12: 0 | E12: =+ProjectBudget[[#This Row],[BUDGET]]-ProjectBudget[[#This Row],[SPENT TO DATE]] -> 0
B13: Travel and subsistence | C13: 0 | D13: 0 | E13: =+ProjectBudget[[#This Row],[BUDGET]]-ProjectBudget[[#This Row],[SPENT TO DATE]] -> 0
B14: External Consultancy | C14: 0 | D14: 0 | E14: =+ProjectBudget[[#This Row],[BUDGET]]-ProjectBudget[[#This Row],[SPENT TO DATE]] -> 0
B15: Communication | C15: 0 | D15: 0 | E15: =+ProjectBudget[[#This Row],[BUDGET]]-ProjectBudget[[#This Row],[SPENT TO DATE]] -> 0
B16: Professional memberships | C16: 0 | D16: 0 | E16: =+ProjectBudget[[#This Row],[BUDGET]]-ProjectBudget[[#This Row],[SPENT TO DATE]] -> 0
B17: Software tools | C17: 0 | D17: 0 | E17: =+ProjectBudget[[#This Row],[BUDGET]]-ProjectBudget[[#This Row],[SPENT TO DATE]] -> 0
B18: Hardware | C18: 0 | D18: 0 | E18: =+ProjectBudget[[#This Row],[BUDGET]]-ProjectBudget[[#This Row],[SPENT TO DATE]] -> 0
B19: Offices and furniture | C19: 0 | D19: 0 | E19: =+ProjectBudget[[#This Row],[BUDGET]]-ProjectBudget[[#This Row],[SPENT TO DATE]] -> 0
B20: Internal auditing | C20: 0 | D20: 0 | E20: =+ProjectBudget[[#This Row],[BUDGET]]-ProjectBudget[[#This Row],[SPENT TO DATE]] -> 0
B21: Certification auditing | C21: 0 | D21: 0 | E21: =+ProjectBudget[[#This Row],[BUDGET]]-ProjectBudget[[#This Row],[SPENT TO DATE]] -> 0
B22: Total | C22: =SUBTOTAL(109,ProjectBudget[BUDGET]) -> 0 | D22: =SUBTOTAL(109,ProjectBudget[SPENT TO DATE]) -> 0 | E22: =SUBTOTAL(109,ProjectBudget[BUDGET REMAINING]) -> 0

Sheet Project Gantt Chart
B8: Project Timeline
B9: =TEXT(MIN(E15:E49),"d-mmmm-yyyy")&" to "&TEXT(MAX(G15:G49),"d-mmmm-yyyy") -> 0-January-1900 to 0-January-1900 | J9: To refresh chart data, click on “Refresh All” on the Data ribbon.
B11: Date display slider | J11: Not started | N11: In progress | R11: Completed | V11: Weekends (Sat - Sun)
B14: REF | C14: TASK | D14: RESOURCE | E14: START DATE | F14: WORK DAYS | G14: END DATE | H14: COMPLETED DAYS | I14: PROGRESS | J14: =MIN(E15:E38)+'Scroll Bar'!B7 -> 0 | K14: =J14+1 -> 1 | L14: =K14+1 -> 2 | M14: =L14+1 -> 3 | N14: =M14+1 -> 4 | O14: =N14+1 -> 5 | P14: =O14+1 -> 6 | Q14: =P14+1 -> 7 | R14: =Q14+1 -> 8 | ... AI14: =AH14+1 -> 25
B15: 1 | C15: Project initiation | D15: Project Mgr | E15: (blank) | F15: 0 | H15: 0
B16: 2 | C16: Define proposed scope of BCMS | D16: Top Mgt,BC Manager | E16: (blank) | F16: 0 | H16: 0
B17: 3 | C17: Perform gap assessment | D17: BC Manager,Business Reps | E17: (blank) | F17: 0 | H17: 0
B18: 4 | C18: Obtain Top Management commitment | D18: BC Manager,Project Mgr,Top Mgt | E18: (blank) | F18: 0 | H18: 0
B19: 5 | C19: Establish BCMS document control | D19: BC Manager,Project Mgr | E19: (blank) | F19: 0 | H19: 0
B20: 6 | C20: Define business continuity policy | D20: BC Manager,Top Mgt | E20: (blank) | F20: 0 | H20: 0
B21: 7 | C21: Document context of the organization | D21: BC Manager,Top Mgt | E21: (blank) | F21: 0 | H21: 0
B22: 8 | C22: Agree business continuity objectives | D22: BC Manager,Top Mgt | E22: (blank) | F22: 0 | H22: 0
B23: 9 | C23: Define roles, responsibilities and authorities | D23: BC Manager,Top Mgt | E23: (blank) | F23: 0 | H23: 0
B24: 10 | C24: Competence and training needs assessment | D24: BC Manager,Business Reps | E24: (blank) | F24: 0 | H24: 0
B25: 11 | C25: Conduct business impact analysis | D25: BC Manager,Business Reps,CIO | E25: (blank) | F25: 0 | H25: 0
B26: 12 | C26: Perform risk assessment | D26: BC Manager,Top Mgt,CIO | E26: (blank) | F26: 0 | H26: 0
... B38: 24 | C38: Post Project Review | D38: Project Mgr,BC Manager,Top Mgt | E38: (blank) | F38: 0 | H38: 0
B39: Grand Total

Sheet Project Dashboard
B8: Project Dashboard
B9: To refresh chart data, click on “Refresh All” on the Data ribbon.
B11: Project timeline: | D11: =TEXT(MIN('Project Gantt Chart'!E15:E49),"d-mmmm-yyyy")&" to "&TEXT(MAX('Project Gantt Chart'!G15:G49),"d-mmmm-yyyy") -> 0-January-1900 to 0-January-1900
B14: Project tasks and progress
B36: Project budget overview

Sheet Tasks & Progress Pivots
B4: Project tasks and progress
B6: Count of REF | E6: Task Status | F6: Task Progress | I6: Project Days | L6: Project Days | M6: %
B7: 24 | E7: Not Started | F7: =COUNTIF('Project Gantt Chart'!I15:I214,"="&0) -> 0 | I7: Completed Work Days | J7: 0 | L7: Days Completed | M7: =GETPIVOTDATA("Completed Work Days",$I$6)/GETPIVOTDATA("Total Work Days",$I$6) -> #DIV/0!
E8: In Progress | F8: =COUNTIFS('Project Gantt Chart'!I15:I214,"<>"&0,'Project Gantt Chart'!I15:I214,"<"&1) -> 0 | I8: Total Work Days | J8: 0 | L8: Days Remaining | M8: =1-M7 -> #DIV/0!
E9: Completed | F9: =COUNTIF('Project Plan'!J11:J34,"="&1) -> 0
E10: Remaining | F10: =F7+F8 -> 0
E11: Total Tasks | F11: =SUM(F9:F10) -> 0
E13: Task Status | F13: Sum of Task Progress
E14: Total Tasks | F14: 0
E15: Completed | F15: 0
E16: Remaining | F16: 0
E17: Not Started | F17: 0
E18: In Progress | F18: 0

Sheet Budget Pivots
B4: Project budget overview
B6: ITEM | C6: Budget | D6: Spent to date | E6: Budget remaining | L6: Values
B7: Certification auditing | C7: 0 | D7: 0 | E7: 0 | L7: Spent to date | M7: 0
B8: Communication | C8: 0 | D8: 0 | E8: 0 | L8: Budget remaining | M8: 0
B9: External Consultancy | C9: 0 | D9: 0 | E9: 0 | L9: Budget | M9: 0
B10: Hardware | C10: 0 | D10: 0 | E10: 0
B11: Internal auditing | C11: 0 | D11: 0 | E11: 0
B12: Internal resources | C12: 0 | D12: 0 | E12: 0
B13: Offices and furniture | C13: 0 | D13: 0 | E13: 0
B14: Professional memberships | C14: 0 | D14: 0 | E14: 0
B15: Software tools | C15: 0 | D15: 0 | E15: 0
B16: Training | C16: 0 | D16: 0 | E16: 0
B17: Travel and subsistence | C17: 0 | D17: 0 | E17: 0
B18: Grand Total | C18: 0 | D18: 0 | E18: 0

Sheet Scroll Bar
B4: Scroll Bar
B6: Scroll Bar
B7: 0
